sanic_pydantic/__init__.py
sanic_pydantic/helpers.py
sanic_pydantic/request_validator.py
sanicpydantic-0.0.3.dist-info/METADATA
sanicpydantic-0.0.3.dist-info/WHEEL
sanicpydantic-0.0.3.dist-info/top_level.txt
sanicpydantic-0.0.3.dist-info/RECORD
