Metadata-Version: 2.1
Name: sanicpydantic
Version: 0.0.3
Summary: Pydantic validation for Sanic framework
Home-page: https://github.com/qwanysh/sanic_pydantic
Author: Kuanysh Beisembayev
Author-email: kuanysh.beisembayev@gmail.com
License: UNKNOWN
Platform: UNKNOWN
Classifier: Programming Language :: Python :: 3
Requires-Dist: sanic
Requires-Dist: pydantic
